odoo/addons/hr_expense_payment_difference/README.rst
odoo/addons/hr_expense_payment_difference/__init__.py
odoo/addons/hr_expense_payment_difference/__manifest__.py
odoo/addons/hr_expense_payment_difference/i18n/hr_expense_payment_difference.pot
odoo/addons/hr_expense_payment_difference/models/__init__.py
odoo/addons/hr_expense_payment_difference/models/account_payment.py
odoo/addons/hr_expense_payment_difference/models/hr_expense.py
odoo/addons/hr_expense_payment_difference/readme/CONTRIBUTORS.rst
odoo/addons/hr_expense_payment_difference/readme/DESCRIPTION.rst
odoo/addons/hr_expense_payment_difference/readme/USAGE.rst
odoo/addons/hr_expense_payment_difference/static/description/icon.png
odoo/addons/hr_expense_payment_difference/static/description/index.html
odoo/addons/hr_expense_payment_difference/tests/__init__.py
odoo/addons/hr_expense_payment_difference/tests/test_hr_expense_payment_difference.py
odoo/addons/hr_expense_payment_difference/wizards/__init__.py
odoo/addons/hr_expense_payment_difference/wizards/hr_expense_sheet_register_payment.py
odoo/addons/hr_expense_payment_difference/wizards/hr_expense_sheet_register_payment.xml
odoo12_addon_hr_expense_payment_difference-12.0.1.1.0.dist-info/METADATA
odoo12_addon_hr_expense_payment_difference-12.0.1.1.0.dist-info/WHEEL
odoo12_addon_hr_expense_payment_difference-12.0.1.1.0.dist-info/top_level.txt
odoo12_addon_hr_expense_payment_difference-12.0.1.1.0.dist-info/RECORD
